metaxy/__init__.py
metaxy/_decorators.py
metaxy/_hashing.py
metaxy/_packaging.py
metaxy/_utils.py
metaxy/_version.py
metaxy/cli/app.py
metaxy/cli/config.py
metaxy/cli/console.py
metaxy/cli/context.py
metaxy/cli/graph.py
metaxy/cli/graph_diff.py
metaxy/cli/list.py
metaxy/cli/mcp.py
metaxy/cli/metadata.py
metaxy/cli/migrations.py
metaxy/cli/utils.py
metaxy/config.py
metaxy/entrypoints.py
metaxy/ext/__init__.py
metaxy/ext/dagster/__init__.py
metaxy/ext/dagster/cleanup.py
metaxy/ext/dagster/constants.py
metaxy/ext/dagster/dagster_type.py
metaxy/ext/dagster/io_manager.py
metaxy/ext/dagster/metaxify.py
metaxy/ext/dagster/observable.py
metaxy/ext/dagster/observation_job.py
metaxy/ext/dagster/resources.py
metaxy/ext/dagster/selection.py
metaxy/ext/dagster/table_metadata.py
metaxy/ext/dagster/utils.py
metaxy/ext/mcp/__init__.py
metaxy/ext/mcp/server.py
metaxy/ext/ray/__init__.py
metaxy/ext/ray/datasink.py
metaxy/ext/ray/datasource.py
metaxy/ext/sqlalchemy/__init__.py
metaxy/ext/sqlalchemy/config.py
metaxy/ext/sqlalchemy/plugin.py
metaxy/ext/sqlmodel/__init__.py
metaxy/ext/sqlmodel/config.py
metaxy/ext/sqlmodel/plugin.py
metaxy/graph/__init__.py
metaxy/graph/describe.py
metaxy/graph/diff/__init__.py
metaxy/graph/diff/diff_models.py
metaxy/graph/diff/differ.py
metaxy/graph/diff/models.py
metaxy/graph/diff/rendering/__init__.py
metaxy/graph/diff/rendering/base.py
metaxy/graph/diff/rendering/cards.py
metaxy/graph/diff/rendering/formatter.py
metaxy/graph/diff/rendering/graphviz.py
metaxy/graph/diff/rendering/mermaid.py
metaxy/graph/diff/rendering/rich.py
metaxy/graph/diff/rendering/theme.py
metaxy/graph/diff/traversal.py
metaxy/graph/status.py
metaxy/graph/utils.py
metaxy/metadata_store/__init__.py
metaxy/metadata_store/_ducklake_support.py
metaxy/metadata_store/base.py
metaxy/metadata_store/bigquery.py
metaxy/metadata_store/clickhouse.py
metaxy/metadata_store/delta.py
metaxy/metadata_store/duckdb.py
metaxy/metadata_store/exceptions.py
metaxy/metadata_store/ibis.py
metaxy-0.0.1.dev32.dist-info/WHEEL
metaxy-0.0.1.dev32.dist-info/entry_points.txt
metaxy-0.0.1.dev32.dist-info/METADATA
metaxy-0.0.1.dev32.dist-info/RECORD
