Metadata-Version: 2.3
Name: metaxy
Version: 0.0.1.dev32
Summary: Pluggable versioned metadata management for incremental multi-modal pipelines.
Author: Daniel Gafni
Author-email: Daniel Gafni <danielgafni16@gmail.com>
Classifier: Development Status :: 2 - Pre-Alpha
Classifier: License :: OSI Approved :: Apache Software License
Classifier: Programming Language :: Python :: 3
Classifier: Programming Language :: Python :: 3.10
Classifier: Programming Language :: Python :: 3.11
Classifier: Programming Language :: Python :: 3.12
Classifier: Programming Language :: Python :: 3.13
Classifier: Typing :: Typed
Requires-Dist: cyclopts>=4.4.0
Requires-Dist: narwhals>=2.14.0
Requires-Dist: platformdirs>=4.5.0
Requires-Dist: polars>=1.35.0
Requires-Dist: polars-hash>=0.5.1
Requires-Dist: pydantic>=2.11.9
Requires-Dist: pydantic-settings>=2.11.0
Requires-Dist: python-dotenv>=1.0.0
Requires-Dist: pyyaml>=6.0.0
Requires-Dist: sqlglot>=28.1.0
Requires-Dist: tomli>=2.3.0
Requires-Dist: rich>=13.0.0
Requires-Dist: packaging>=25.0
Requires-Dist: tomli-w>=1.2.0
Requires-Dist: ibis-framework[bigquery]>=11.0.0 ; extra == 'bigquery'
Requires-Dist: ibis-framework[clickhouse]>=11.0.0 ; extra == 'clickhouse'
Requires-Dist: dagster>=1.12.3 ; extra == 'dagster'
Requires-Dist: deltalake>=1.2.1 ; extra == 'delta'
Requires-Dist: ibis-framework>=11.0.0 ; extra == 'delta'
Requires-Dist: ibis-framework[duckdb]>=11.0.0 ; extra == 'duckdb'
Requires-Dist: duckdb>=1.4.1 ; extra == 'duckdb'
Requires-Dist: pygraphviz>=1.14 ; extra == 'graphviz'
Requires-Dist: pyarrow>=18.0.0 ; extra == 'ibis'
Requires-Dist: ibis-framework>=11.0.0 ; extra == 'ibis'
Requires-Dist: lancedb>=0.15.0 ; extra == 'lancedb'
Requires-Dist: polars>=1.36.1 ; extra == 'lancedb'
Requires-Dist: fastmcp>=2.0.0 ; extra == 'mcp'
Requires-Dist: mermaid-py>=0.8.0 ; extra == 'mermaid'
Requires-Dist: ray>2.36.0 ; (python_full_version < '3.13' and extra == 'ray') or (sys_platform != 'win32' and extra == 'ray')
Requires-Dist: sqlmodel>=0.0.27 ; extra == 'sqlmodel'
Requires-Python: >=3.10
Project-URL: Documentation, https://metaxy.dev
Project-URL: Issues, https://github.com/anam-org/metaxy/issues
Project-URL: Repository, https://github.com/anam-org/metaxy
Provides-Extra: bigquery
Provides-Extra: clickhouse
Provides-Extra: dagster
Provides-Extra: delta
Provides-Extra: duckdb
Provides-Extra: graphviz
Provides-Extra: ibis
Provides-Extra: lancedb
Provides-Extra: mcp
Provides-Extra: mermaid
Provides-Extra: ray
Provides-Extra: sqlmodel
